discordbridge
