Metadata-Version: 2.1
Name: discord-bridge
Version: 1.0.0a6
Summary: HTTP bridge for the Discord API
Home-page: https://gitlab.com/ErikKalkoken/discord-bridge
Author: Erik Kalkoken
Author-email: kalkoken87@gmail.com
License: MIT
Platform: UNKNOWN
Classifier: Intended Audience :: Developers
Classifier: License :: OSI Approved :: MIT License
Classifier: Operating System :: OS Independent
Classifier: Programming Language :: Python
Classifier: Programming Language :: Python :: 3.6
Classifier: Programming Language :: Python :: 3.7
Classifier: Programming Language :: Python :: 3.8
Requires-Python: ~=3.6
